multiunit/__init__.py
multiunit/__main__.py
multiunit/program.py
multiunit-0.1.1.dist-info/LICENSE
multiunit-0.1.1.dist-info/METADATA
multiunit-0.1.1.dist-info/WHEEL
multiunit-0.1.1.dist-info/top_level.txt
multiunit-0.1.1.dist-info/RECORD
